MANIFEST.in
README.rst
setup.py
collective/__init__.py
collective.i18nreport.egg-info/PKG-INFO
collective.i18nreport.egg-info/SOURCES.txt
collective.i18nreport.egg-info/dependency_links.txt
collective.i18nreport.egg-info/entry_points.txt
collective.i18nreport.egg-info/namespace_packages.txt
collective.i18nreport.egg-info/not-zip-safe
collective.i18nreport.egg-info/requires.txt
collective.i18nreport.egg-info/top_level.txt
collective/i18nreport/__init__.py
collective/i18nreport/coverage.py
collective/i18nreport/formatters.py
collective/i18nreport/template.html
collective/i18nreport/utils.py
collective/i18nreport/tests/__init__.py
collective/i18nreport/tests/helpers.py
collective/i18nreport/tests/test_coverage.py
collective/i18nreport/tests/test_formatters.py
collective/i18nreport/tests/test_utils.py
collective/i18nreport/tests/example/foo/i18n/plone-nl.po
collective/i18nreport/tests/example/foo/i18n/plone.pot
collective/i18nreport/tests/example/foo/locales/locales/linguaplone.pot
collective/i18nreport/tests/example/foo/locales/locales/plone.pot
collective/i18nreport/tests/example/foo/locales/locales/nl/LC_MESSAGES/linguaplone.po
collective/i18nreport/tests/example/foo/locales/locales/nl/LC_MESSAGES/plone.po
docs/HISTORY.txt