Metadata-Version: 1.1
Name: collective.i18nreport
Version: 1.2
Summary: Internationalization coverage report
Home-page: https://github.com/collective/collective.i18nreport
Author: Jonas Baumann
Author-email: jone@jone.ch
License: GPL2
Keywords: i18n coverage
Platform: UNKNOWN
Classifier: Programming Language :: Python
Classifier: Programming Language :: Python :: 2.6
Classifier: Programming Language :: Python :: 2.7
